mofox_wire/__init__.py
mofox_wire/adapter_utils.py
mofox_wire/api.py
mofox_wire/builder.py
mofox_wire/codec.py
mofox_wire/router.py
mofox_wire/runtime.py
mofox_wire/types.py
mofox_wire/transport/__init__.py
mofox_wire/transport/http_client.py
mofox_wire/transport/http_server.py
mofox_wire/transport/ws_client.py
mofox_wire/transport/ws_server.py
mofox_wire-0.1.5.dist-info/licenses/LICENSE
mofox_wire-0.1.5.dist-info/METADATA
mofox_wire-0.1.5.dist-info/WHEEL
mofox_wire-0.1.5.dist-info/top_level.txt
mofox_wire-0.1.5.dist-info/RECORD
