Metadata-Version: 2.4
Name: mofox-wire
Version: 0.1.5
Summary: Messaging wire for MoFox Bot with HTTP/WebSocket transports and routing helpers.
Home-page: https://github.com/mofox-bot/mofox-wire
Author: MoFox Team
Author-email: 
License:                     GNU GENERAL PUBLIC LICENSE
Project-URL: Homepage, https://github.com/mofox-bot/mofox-wire
Platform: any
Requires-Python: >=3.11
License-File: LICENSE
Requires-Dist: aiohttp>=3.12.0
Requires-Dist: fastapi>=0.116.0
Requires-Dist: orjson>=3.10.0
Requires-Dist: uvicorn>=0.35.0
Requires-Dist: websockets>=15.0.1
Dynamic: home-page
Dynamic: license-file
Dynamic: platform
Dynamic: requires-python
